sphinxcontrib.asciinema-0.3.3-nspkg.pth
sphinxcontrib/asciinema/__init__.py
sphinxcontrib/asciinema/asciinema.py
sphinxcontrib/asciinema/_static/PowerlineSymbols.otf
sphinxcontrib/asciinema/_static/asciinema-custom.css
sphinxcontrib/asciinema/_static/asciinema-player_2.6.1.css
sphinxcontrib/asciinema/_static/asciinema-player_2.6.1.js
sphinxcontrib.asciinema-0.3.3.dist-info/LICENSE
sphinxcontrib.asciinema-0.3.3.dist-info/METADATA
sphinxcontrib.asciinema-0.3.3.dist-info/WHEEL
sphinxcontrib.asciinema-0.3.3.dist-info/namespace_packages.txt
sphinxcontrib.asciinema-0.3.3.dist-info/top_level.txt
sphinxcontrib.asciinema-0.3.3.dist-info/RECORD
