Metadata-Version: 2.1
Name: sphinxcontrib.asciinema
Version: 0.3.3
Summary: Embed asciinema casts in your Sphinx docs
Home-page: https://github.com/divi255/sphinxcontrib.asciinema
License: MIT
Platform: UNKNOWN
Classifier: Programming Language :: Python
Classifier: License :: OSI Approved :: MIT License
Classifier: Programming Language :: Python :: 3
Classifier: Topic :: Software Development :: Documentation
Requires-Dist: sphinx
